Workbook
Name NativeTimeline_fixed_OD: #N/A
Name Slicer_Region4: #N/A

Sheet global_data
A1: Order ID | B1: fixed_OD | C1: Salesperson ID | D1: Salesperson Name | E1: Region | F1: City | G1: Product ID | H1: Product Name | I1: Category | J1: Unit Price | K1: Quantity | L1: Discount | M1: Revenue | N1: Payment Mode | O1: Order Status | P1: R/D | Q1: Check overdiscounting | R1: Original revenue | S1: revenue lost due to discount | T1: average order value
A2: ORD01215 | B2: 45456 | C2: SP03 | D2: Ravi Kumar | E2: East | F2: Kolkata | G2: PRD015 | H2: Dettol Liquid Soap 250ml | I2: Personal Care | J2: 145 | K2: 12 | L2: 0.11 | M2: 1548.6 | N2: Net Banking | O2: Delivered | P2: =global_data!$M2/global_data!$L2 -> 14078.182 | Q2: =IFERROR(global_data!$P2,0) -> 14078.182 | R2: =global_data!$M2/(1-global_data!$L2) -> 1740 | S2: =global_data!$R2-global_data!$M2 -> 191.4
A3: ORD01250 | B3: 45548 | C3: SP012 | D3: Sneha Patil | E3: West | F3: Ahmedabad | G3: PRD005 | H3: Bajaj Mixer Grinder 750W | I3: Appliances | J3: 2100 | K3: 17 | L3: 0.06 | M3: 33558 | N3: Debit Card | O3: Pending | P3: =global_data!$M3/global_data!$L3 -> 559300 | Q3: =IFERROR(global_data!$P3,0) -> 559300 | R3: =global_data!$M3/(1-global_data!$L3) -> 35700 | S3: =global_data!$R3-global_data!$M3 -> 2142
A4: ORD01262 | B4: 45552 | C4: SP05 | D4: Suresh Pillai | E4: South | F4: Hyderabad | G4: PRD019 | H4: Classmate A4 Notebook 200pg | I4: Stationery | J4: 85 | K4: 20 | L4: 0.03 | M4: 1649 | N4: EMI | O4: Delivered | P4: =global_data!$M4/global_data!$L4 -> 54966.667 | Q4: =IFERROR(global_data!$P4,0) -> 54966.667 | R4: =global_data!$M4/(1-global_data!$L4) -> 1700 | S4: =global_data!$R4-global_data!$M4 -> 51
A5: ORD01301 | B5: 45445 | C5: SP011 | D5: Nikhil Joshi | E5: East | F5: Kolkata | G5: PRD008 | H5: American Tourister Trolley | I5: Bags | J5: 4999 | K5: 3 | L5: 0.21 | M5: 11847.63 | N5: Debit Card | O5: Delivered | P5: =global_data!$M5/global_data!$L5 -> 56417.286 | Q5: =IFERROR(global_data!$P5,0) -> 56417.286 | R5: =global_data!$M5/(1-global_data!$L5) -> 14997 | S5: =global_data!$R5-global_data!$M5 -> 3149.37
A6: ORD01373 | B6: 45433 | C6: SP011 | D6: Nikhil Joshi | E6: East | F6: Ranchi | G6: PRD010 | H6: Bata Ladies Sandals | I6: Footwear | J6: 1299 | K6: 7 | L6: 0.16 | M6: 7638.12 | N6: Debit Card | O6: Delivered | P6: =global_data!$M6/global_data!$L6 -> 47738.25 | Q6: =IFERROR(global_data!$P6,0) -> 47738.25 | R6: =global_data!$M6/(1-global_data!$L6) -> 9093 | S6: =global_data!$R6-global_data!$M6 -> 1454.88
A7: ORD01411 | B7: 45317 | C7: SP07 | D7: Rohit Verma | E7: East | F7: Ranchi | G7: PRD009 | H7: Woodland Men Boots | I7: Footwear | J7: 3499 | K7: 6 | L7: 0.01 | M7: 20784.06 | N7: Credit Card | O7: Delivered | P7: =global_data!$M7/global_data!$L7 -> 2078406 | Q7: =IFERROR(global_data!$P7,0) -> 2078406 | R7: =global_data!$M7/(1-global_data!$L7) -> 20994 | S7: =global_data!$R7-global_data!$M7 -> 209.94
A8: ORD01523 | B8: 45592 | C8: SP08 | D8: Kavitha Reddy | E8: West | F8: Ahmedabad | G8: PRD005 | H8: Bajaj Mixer Grinder 750W | I8: Appliances | J8: 2100 | K8: 2 | L8: 0.05 | M8: 3990 | N8: EMI | O8: Delivered | P8: =global_data!$M8/global_data!$L8 -> 79800 | Q8: =IFERROR(global_data!$P8,0) -> 79800 | R8: =global_data!$M8/(1-global_data!$L8) -> 4200 | S8: =global_data!$R8-global_data!$M8 -> 210
A9: ORD01674 | B9: 45374 | C9: SP04 | D9: Fatima Sheikh | E9: West | F9: Nagpur | G9: PRD018 | H9: Maggi Noodles Pack of 12 | I9: Food & Bev | J9: 144 | K9: 17 | L9: 0.23 | M9: 1884.96 | N9: EMI | O9: Delivered | P9: =global_data!$M9/global_data!$L9 -> 8195.4783 | Q9: =IFERROR(global_data!$P9,0) -> 8195.4783 | R9: =global_data!$M9/(1-global_data!$L9) -> 2448 | S9: =global_data!$R9-global_data!$M9 -> 563.04
A10: ORD01777 | B10: 45623 | C10: SP05 | D10: Suresh Pillai | E10: South | F10: Coimbatore | G10: PRD009 | H10: Woodland Men Boots | I10: Footwear | J10: 3499 | K10: 7 | L10: 0.01 | M10: 24248.07 | N10: Net Banking | O10: Delivered | P10: =global_data!$M10/global_data!$L10 -> 2424807 | Q10: =IFERROR(global_data!$P10,0) -> 2424807 | R10: =global_data!$M10/(1-global_data!$L10) -> 24493 | S10: =global_data!$R10-global_data!$M10 -> 244.93
A11: ORD01846 | B11: 45563 | C11: SP010 | D11: Divya Iyer | E11: South | F11: Hyderabad | G11: PRD017 | H11: Tata Gold Tea 500g | I11: Food & Bev | J11: 299 | K11: 8 | L11: 0.23 | M11: 1841.84 | N11: Cash | O11: Delivered | P11: =global_data!$M11/global_data!$L11 -> 8008 | Q11: =IFERROR(global_data!$P11,0) -> 8008 | R11: =global_data!$M11/(1-global_data!$L11) -> 2392 | S11: =global_data!$R11-global_data!$M11 -> 550.16
A12: ORD01850 | B12: 45378 | C12: SP07 | D12: Rohit Verma | E12: East | F12: Guwahati | G12: PRD015 | H12: Dettol Liquid Soap 250ml | I12: Personal Care | J12: 145 | K12: 10 | L12: 0.05 | M12: 1377.5 | N12: Debit Card | O12: Returned | P12: =global_data!$M12/global_data!$L12 -> 27550 | Q12: =IFERROR(global_data!$P12,0) -> 27550 | R12: =global_data!$M12/(1-global_data!$L12) -> 1450 | S12: =global_data!$R12-global_data!$M12 -> 72.5
A13: ORD01904 | B13: 45619 | C13: SP07 | D13: Rohit Verma | E13: East | F13: Ranchi | G13: PRD009 | H13: Woodland Men Boots | I13: Footwear | J13: 3499 | K13: 20 | L13: 0.15 | M13: 59483 | N13: Cash | O13: Delivered | P13: =global_data!$M13/global_data!$L13 -> 396553.33 | Q13: =IFERROR(global_data!$P13,0) -> 396553.33 | R13: =global_data!$M13/(1-global_data!$L13) -> 69980 | S13: =global_data!$R13-global_data!$M13 -> 10497
... A2401: ORD03383 | B2401: 45444 | C2401: SP06 | D2401: Anjali Mehta | E2401: North | F2401: Agra | G2401: PRD009 | H2401: Woodland Men Boots | I2401: Footwear | J2401: 3499 | K2401: 11 | L2401: 0.29 | M2401: 27327.19 | N2401: Cash | O2401: Delivered | P2401: =global_data!$M2401/global_data!$L2401 -> 94231.69 | Q2401: =IFERROR(global_data!$P2401,0) -> 94231.69 | R2401: =global_data!$M2401/(1-global_data!$L2401) -> 38489 | S2401: =global_data!$R2401-global_data!$M2401 -> 11161.81

Sheet Sheet1
A1: Order ID | B1: fixed_OD | C1: Salesperson ID | D1: Salesperson Name | E1: Region | F1: City | G1: Product ID | H1: Product Name | I1: Category | J1: Unit Price | K1: Quantity | L1: Discount | M1: Revenue | N1: Payment Mode | O1: Order Status
A2: ORD01215 | B2: 45456 | C2: SP03 | D2: Ravi Kumar | E2: East | F2: Kolkata | G2: PRD015 | H2: Dettol Liquid Soap 250ml | I2: Personal Care | J2: 145 | K2: 12 | L2: 0.11 | M2: 1548.6 | N2: Net Banking | O2: Delivered
A3: ORD01250 | B3: 45548 | C3: SP012 | D3: Sneha Patil | E3: West | F3: Ahmedabad | G3: PRD005 | H3: Bajaj Mixer Grinder 750W | I3: Appliances | J3: 2100 | K3: 17 | L3: 0.06 | M3: 33558 | N3: Debit Card | O3: Pending
A4: ORD01262 | B4: 45552 | C4: SP05 | D4: Suresh Pillai | E4: South | F4: Hyderabad | G4: PRD019 | H4: Classmate A4 Notebook 200pg | I4: Stationery | J4: 85 | K4: 20 | L4: 0.03 | M4: 1649 | N4: EMI | O4: Delivered
A5: ORD01301 | B5: 45445 | C5: SP011 | D5: Nikhil Joshi | E5: East | F5: Kolkata | G5: PRD008 | H5: American Tourister Trolley | I5: Bags | J5: 4999 | K5: 3 | L5: 0.21 | M5: 11847.63 | N5: Debit Card | O5: Delivered
A6: ORD01373 | B6: 45433 | C6: SP011 | D6: Nikhil Joshi | E6: East | F6: Ranchi | G6: PRD010 | H6: Bata Ladies Sandals | I6: Footwear | J6: 1299 | K6: 7 | L6: 0.16 | M6: 7638.12 | N6: Debit Card | O6: Delivered
A7: ORD01411 | B7: 45317 | C7: SP07 | D7: Rohit Verma | E7: East | F7: Ranchi | G7: PRD009 | H7: Woodland Men Boots | I7: Footwear | J7: 3499 | K7: 6 | L7: 0.01 | M7: 20784.06 | N7: Credit Card | O7: Delivered
A8: ORD01523 | B8: 45592 | C8: SP08 | D8: Kavitha Reddy | E8: West | F8: Ahmedabad | G8: PRD005 | H8: Bajaj Mixer Grinder 750W | I8: Appliances | J8: 2100 | K8: 2 | L8: 0.05 | M8: 3990 | N8: EMI | O8: Delivered
A9: ORD01674 | B9: 45374 | C9: SP04 | D9: Fatima Sheikh | E9: West | F9: Nagpur | G9: PRD018 | H9: Maggi Noodles Pack of 12 | I9: Food & Bev | J9: 144 | K9: 17 | L9: 0.23 | M9: 1884.96 | N9: EMI | O9: Delivered
A10: ORD01777 | B10: 45623 | C10: SP05 | D10: Suresh Pillai | E10: South | F10: Coimbatore | G10: PRD009 | H10: Woodland Men Boots | I10: Footwear | J10: 3499 | K10: 7 | L10: 0.01 | M10: 24248.07 | N10: Net Banking | O10: Delivered
A11: ORD01846 | B11: 45563 | C11: SP010 | D11: Divya Iyer | E11: South | F11: Hyderabad | G11: PRD017 | H11: Tata Gold Tea 500g | I11: Food & Bev | J11: 299 | K11: 8 | L11: 0.23 | M11: 1841.84 | N11: Cash | O11: Delivered
A12: ORD01850 | B12: 45378 | C12: SP07 | D12: Rohit Verma | E12: East | F12: Guwahati | G12: PRD015 | H12: Dettol Liquid Soap 250ml | I12: Personal Care | J12: 145 | K12: 10 | L12: 0.05 | M12: 1377.5 | N12: Debit Card | O12: Returned
A13: ORD01904 | B13: 45619 | C13: SP07 | D13: Rohit Verma | E13: East | F13: Ranchi | G13: PRD009 | H13: Woodland Men Boots | I13: Footwear | J13: 3499 | K13: 20 | L13: 0.15 | M13: 59483 | N13: Cash | O13: Delivered
... A2401: ORD03383 | B2401: 45444 | C2401: SP06 | D2401: Anjali Mehta | E2401: North | F2401: Agra | G2401: PRD009 | H2401: Woodland Men Boots | I2401: Footwear | J2401: 3499 | K2401: 11 | L2401: 0.29 | M2401: 27327.19 | N2401: Cash | O2401: Delivered

Sheet Sheet2
A1: Order ID | B1: fixed_OD | C1: Salesperson ID | D1: Salesperson Name | E1: Region | F1: City | G1: Product ID | H1: Product Name | I1: Category | J1: Unit Price | K1: Quantity | L1: Discount | M1: Revenue | N1: Payment Mode | O1: Order Status | P1: R/D | Q1: Check overdiscounting | R1: Original revenue | S1: revenue lost due to discount
A2: ORD01215 | B2: 45456 | C2: SP03 | D2: Ravi Kumar | E2: East | F2: Kolkata | G2: PRD015 | H2: Dettol Liquid Soap 250ml | I2: Personal Care | J2: 145 | K2: 12 | L2: 0.11 | M2: 1548.6 | N2: Net Banking | O2: Delivered | P2: 14078.182 | Q2: 14078.182 | R2: 1740 | S2: 191.4
A3: ORD01250 | B3: 45548 | C3: SP012 | D3: Sneha Patil | E3: West | F3: Ahmedabad | G3: PRD005 | H3: Bajaj Mixer Grinder 750W | I3: Appliances | J3: 2100 | K3: 17 | L3: 0.06 | M3: 33558 | N3: Debit Card | O3: Pending | P3: 559300 | Q3: 559300 | R3: 35700 | S3: 2142
A4: ORD01262 | B4: 45552 | C4: SP05 | D4: Suresh Pillai | E4: South | F4: Hyderabad | G4: PRD019 | H4: Classmate A4 Notebook 200pg | I4: Stationery | J4: 85 | K4: 20 | L4: 0.03 | M4: 1649 | N4: EMI | O4: Delivered | P4: 54966.667 | Q4: 54966.667 | R4: 1700 | S4: 51
A5: ORD01301 | B5: 45445 | C5: SP011 | D5: Nikhil Joshi | E5: East | F5: Kolkata | G5: PRD008 | H5: American Tourister Trolley | I5: Bags | J5: 4999 | K5: 3 | L5: 0.21 | M5: 11847.63 | N5: Debit Card | O5: Delivered | P5: 56417.286 | Q5: 56417.286 | R5: 14997 | S5: 3149.37
A6: ORD01373 | B6: 45433 | C6: SP011 | D6: Nikhil Joshi | E6: East | F6: Ranchi | G6: PRD010 | H6: Bata Ladies Sandals | I6: Footwear | J6: 1299 | K6: 7 | L6: 0.16 | M6: 7638.12 | N6: Debit Card | O6: Delivered | P6: 47738.25 | Q6: 47738.25 | R6: 9093 | S6: 1454.88
A7: ORD01411 | B7: 45317 | C7: SP07 | D7: Rohit Verma | E7: East | F7: Ranchi | G7: PRD009 | H7: Woodland Men Boots | I7: Footwear | J7: 3499 | K7: 6 | L7: 0.01 | M7: 20784.06 | N7: Credit Card | O7: Delivered | P7: 2078406 | Q7: 2078406 | R7: 20994 | S7: 209.94
A8: ORD01523 | B8: 45592 | C8: SP08 | D8: Kavitha Reddy | E8: West | F8: Ahmedabad | G8: PRD005 | H8: Bajaj Mixer Grinder 750W | I8: Appliances | J8: 2100 | K8: 2 | L8: 0.05 | M8: 3990 | N8: EMI | O8: Delivered | P8: 79800 | Q8: 79800 | R8: 4200 | S8: 210
A9: ORD01674 | B9: 45374 | C9: SP04 | D9: Fatima Sheikh | E9: West | F9: Nagpur | G9: PRD018 | H9: Maggi Noodles Pack of 12 | I9: Food & Bev | J9: 144 | K9: 17 | L9: 0.23 | M9: 1884.96 | N9: EMI | O9: Delivered | P9: 8195.4783 | Q9: 8195.4783 | R9: 2448 | S9: 563.04
A10: ORD01777 | B10: 45623 | C10: SP05 | D10: Suresh Pillai | E10: South | F10: Coimbatore | G10: PRD009 | H10: Woodland Men Boots | I10: Footwear | J10: 3499 | K10: 7 | L10: 0.01 | M10: 24248.07 | N10: Net Banking | O10: Delivered | P10: 2424807 | Q10: 2424807 | R10: 24493 | S10: 244.93
A11: ORD01846 | B11: 45563 | C11: SP010 | D11: Divya Iyer | E11: South | F11: Hyderabad | G11: PRD017 | H11: Tata Gold Tea 500g | I11: Food & Bev | J11: 299 | K11: 8 | L11: 0.23 | M11: 1841.84 | N11: Cash | O11: Delivered | P11: 8008 | Q11: 8008 | R11: 2392 | S11: 550.16
A12: ORD01850 | B12: 45378 | C12: SP07 | D12: Rohit Verma | E12: East | F12: Guwahati | G12: PRD015 | H12: Dettol Liquid Soap 250ml | I12: Personal Care | J12: 145 | K12: 10 | L12: 0.05 | M12: 1377.5 | N12: Debit Card | O12: Returned | P12: 27550 | Q12: 27550 | R12: 1450 | S12: 72.5
A13: ORD01904 | B13: 45619 | C13: SP07 | D13: Rohit Verma | E13: East | F13: Ranchi | G13: PRD009 | H13: Woodland Men Boots | I13: Footwear | J13: 3499 | K13: 20 | L13: 0.15 | M13: 59483 | N13: Cash | O13: Delivered | P13: 396553.33 | Q13: 396553.33 | R13: 69980 | S13: 10497
A14: ORD02130 | B14: 45334 | C14: SP05 | D14: Suresh Pillai | E14: South | F14: Bangalore | G14: PRD019 | H14: Classmate A4 Notebook 200pg | I14: Stationery | J14: 85 | K14: 15 | L14: 0.29 | M14: 905.25 | N14: Debit Card | O14: Delivered | P14: 3121.5517 | Q14: 3121.5517 | R14: 1275 | S14: 369.75
A15: ORD02187 | B15: 45296 | C15: SP03 | D15: Ravi Kumar | E15: East | F15: Guwahati | G15: PRD020 | H15: Cello Butterflow Pens Pk10 | I15: Stationery | J15: 75 | K15: 6 | L15: 0 | M15: 450 | N15: Cash | O15: Cancelled | P15: #DIV/0! | Q15: 0 | R15: 450 | S15: 0
A16: ORD02249 | B16: 45366 | C16: SP04 | D16: Fatima Sheikh | E16: West | F16: Pune | G16: PRD015 | H16: Dettol Liquid Soap 250ml | I16: Personal Care | J16: 145 | K16: 8 | L16: 0.1 | M16: 1044 | N16: Debit Card | O16: Delivered | P16: 10440 | Q16: 10440 | R16: 1160 | S16: 116
A17: ORD02292 | B17: 45455 | C17: SP08 | D17: Kavitha Reddy | E17: West | F17: Pune | G17: PRD011 | H17: Peter England Formal Shirt | I17: Clothing | J17: 1199 | K17: 6 | L17: 0.28 | M17: 5179.68 | N17: Net Banking | O17: Delivered | P17: 18498.857 | Q17: 18498.857 | R17: 7194 | S17: 2014.32
A18: ORD02296 | B18: 45315 | C18: SP07 | D18: Rohit Verma | E18: East | F18: Kolkata | G18: PRD017 | H18: Tata Gold Tea 500g | I18: Food & Bev | J18: 299 | K18: 15 | L18: 0.08 | M18: 4126.2 | N18: EMI | O18: Delivered | P18: 51577.5 | Q18: 51577.5 | R18: 4485 | S18: 358.8
A19: ORD02430 | B19: 45588 | C19: SP09 | D19: Manish Gupta | E19: North | F19: Delhi | G19: PRD011 | H19: Peter England Formal Shirt | I19: Clothing | J19: 1199 | K19: 2 | L19: 0.07 | M19: 2230.14 | N19: Net Banking | O19: Cancelled | P19: 31859.143 | Q19: 31859.143 | R19: 2398 | S19: 167.86
A20: ORD02441 | B20: 45539 | C20: SP09 | D20: Manish Gupta | E20: North | F20: Lucknow | G20: PRD010 | H20: Bata Ladies Sandals | I20: Footwear | J20: 1299 | K20: 8 | L20: 0.16 | M20: 8729.28 | N20: Net Banking | O20: Delivered | P20: 54558 | Q20: 54558 | R20: 10392 | S20: 1662.72
A21: ORD02458 | B21: 45558 | C21: SP04 | D21: Fatima Sheikh | E21: West | F21: Mumbai | G21: PRD002 | H21: iPhone 15 128GB | I21: Electronics | J21: 79999 | K21: 9 | L21: 0.29 | M21: 511193.61 | N21: Credit Card | O21: Delivered | P21: 1762736.6 | Q21: 1762736.6 | R21: 719991 | S21: 208797.39
A22: ORD02499 | B22: 45309 | C22: SP011 | D22: Nikhil Joshi | E22: East | F22: Ranchi | G22: PRD008 | H22: American Tourister Trolley | I22: Bags | J22: 4999 | K22: 1 | L22: 0.09 | M22: 4549.09 | N22: Debit Card | O22: Delivered | P22: 50545.444 | Q22: 50545.444 | R22: 4999 | S22: 449.91
A23: ORD02512 | B23: 45435 | C23: SP07 | D23: Rohit Verma | E23: East | F23: Guwahati | G23: PRD010 | H23: Bata Ladies Sandals | I23: Footwear | J23: 1299 | K23: 14 | L23: 0.03 | M23: 17640.42 | N23: Debit Card | O23: Delivered | P23: 588014 | Q23: 588014 | R23: 18186 | S23: 545.58
A24: ORD02521 | B24: 45324 | C24: SP07 | D24: Rohit Verma | E24: East | F24: Kolkata | G24: PRD005 | H24: Bajaj Mixer Grinder 750W | I24: Appliances | J24: 2100 | K24: 1 | L24: 0.05 | M24: 1995 | N24: Debit Card | O24: Delivered | P24: 39900 | Q24: 39900 | R24: 2100 | S24: 105
A25: ORD02573 | B25: 45620 | C25: SP06 | D25: Anjali Mehta | E25: North | F25: Agra | G25: PRD010 | H25: Bata Ladies Sandals | I25: Footwear | J25: 1299 | K25: 14 | L25: 0.18 | M25: 14912.52 | N25: Debit Card | O25: Delivered | P25: 82847.333 | Q25: 82847.333 | R25: 18186 | S25: 3273.48
A26: ORD02658 | B26: 45649 | C26: SP09 | D26: Manish Gupta | E26: North | F26: Chandigarh | G26: PRD017 | H26: Tata Gold Tea 500g | I26: Food & Bev | J26: 299 | K26: 10 | L26: 0.21 | M26: 2362.1 | N26: Cash | O26: Returned | P26: 11248.095 | Q26: 11248.095 | R26: 2990 | S26: 627.9
A27: ORD02682 | B27: 45511 | C27: SP012 | D27: Sneha Patil | E27: West | F27: Mumbai | G27: PRD006 | H27: Whirlpool 7kg Washing Machine | I27: Appliances | J27: 22000 | K27: 12 | L27: 0.26 | M27: 195360 | N27: Cash | O27: Returned | P27: 751384.62 | Q27: 751384.62 | R27: 264000 | S27: 68640
... A58: ORD01448 | B58: 45436 | C58: SP02 | D58: Priya Nair | E58: South | F58: Kochi | G58: PRD008 | H58: American Tourister Trolley | I58: Bags | J58: 4999 | K58: 5 | L58: 0.09 | M58: 22745.45 | N58: Credit Card | O58: Returned | P58: 252727.22 | Q58: 252727.22 | R58: 24995 | S58: 2249.55
A59: ORD01485 | B59: 45612 | C59: SP06 | D59: Anjali Mehta | E59: North | F59: Delhi | G59: PRD008 | H59: American Tourister Trolley | I59: Bags | J59: 4999 | K59: 1 | L59: 0 | M59: 4999 | N59: Net Banking | O59: Pending | P59: #DIV/0! | Q59: 0 | R59: 4999 | S59: 0
A60: ORD01518 | B60: 45486 | C60: SP07 | D60: Rohit Verma | E60: East | F60: Patna | G60: PRD008 | H60: American Tourister Trolley | I60: Bags | J60: 4999 | K60: 17 | L60: 0.24 | M60: 64587.08 | N60: Cash | O60: Delivered | P60: 269112.83 | Q60: 269112.83 | R60: 84983 | S60: 20395.92
A61: ORD01583 | B61: 45297 | C61: SP09 | D61: Manish Gupta | E61: North | F61: Delhi | G61: PRD008 | H61: American Tourister Trolley | I61: Bags | J61: 4999 | K61: 20 | L61: 0.05 | M61: 94981 | N61: EMI | O61: Delivered | P61: 1899620 | Q61: 1899620 | R61: 99980 | S61: 4999
A62: ORD01586 | B62: 45536 | C62: SP05 | D62: Suresh Pillai | E62: South | F62: Kochi | G62: PRD008 | H62: American Tourister Trolley | I62: Bags | J62: 4999 | K62: 20 | L62: 0.29 | M62: 70985.8 | N62: Net Banking | O62: Pending | P62: 244778.62 | Q62: 244778.62 | R62: 99980 | S62: 28994.2
A63: ORD01589 | B63: 45307 | C63: SP08 | D63: Kavitha Reddy | E63: West | F63: Surat | G63: PRD008 | H63: American Tourister Trolley | I63: Bags | J63: 4999 | K63: 11 | L63: 0.29 | M63: 39042.19 | N63: Net Banking | O63: Delivered | P63: 134628.24 | Q63: 134628.24 | R63: 54989 | S63: 15946.81
A64: ORD01602 | B64: 45387 | C64: SP010 | D64: Divya Iyer | E64: South | F64: Bangalore | G64: PRD008 | H64: American Tourister Trolley | I64: Bags | J64: 4999 | K64: 4 | L64: 0.22 | M64: 15596.88 | N64: Debit Card | O64: Delivered | P64: 70894.909 | Q64: 70894.909 | R64: 19996 | S64: 4399.12
A65: ORD01623 | B65: 45422 | C65: SP07 | D65: Rohit Verma | E65: East | F65: Ranchi | G65: PRD008 | H65: American Tourister Trolley | I65: Bags | J65: 4999 | K65: 17 | L65: 0.23 | M65: 65436.91 | N65: EMI | O65: Cancelled | P65: 284508.3 | Q65: 284508.3 | R65: 84983 | S65: 19546.09
A66: ORD01659 | B66: 45406 | C66: SP04 | D66: Fatima Sheikh | E66: West | F66: Mumbai | G66: PRD008 | H66: American Tourister Trolley | I66: Bags | J66: 4999 | K66: 9 | L66: 0.24 | M66: 34193.16 | N66: Net Banking | O66: Delivered | P66: 142471.5 | Q66: 142471.5 | R66: 44991 | S66: 10797.84
A67: ORD01664 | B67: 45582 | C67: SP09 | D67: Manish Gupta | E67: North | F67: Jaipur | G67: PRD008 | H67: American Tourister Trolley | I67: Bags | J67: 4999 | K67: 5 | L67: 0.02 | M67: 24495.1 | N67: Net Banking | O67: Pending | P67: 1224755 | Q67: 1224755 | R67: 24995 | S67: 499.9
A68: ORD01665 | B68: 45338 | C68: SP02 | D68: Priya Nair | E68: South | F68: Kochi | G68: PRD008 | H68: American Tourister Trolley | I68: Bags | J68: 4999 | K68: 14 | L68: 0.09 | M68: 63687.26 | N68: Credit Card | O68: Delivered | P68: 707636.22 | Q68: 707636.22 | R68: 69986 | S68: 6298.74
A69: ORD01683 | B69: 45606 | C69: SP011 | D69: Nikhil Joshi | E69: East | F69: Bhubaneswar | G69: PRD008 | H69: American Tourister Trolley | I69: Bags | J69: 4999 | K69: 14 | L69: 0.07 | M69: 65086.98 | N69: Credit Card | O69: Delivered | P69: 929814 | Q69: 929814 | R69: 69986 | S69: 4899.02
A70: ORD01693 | B70: 45637 | C70: SP08 | D70: Kavitha Reddy | E70: West | F70: Mumbai | G70: PRD008 | H70: American Tourister Trolley | I70: Bags | J70: 4999 | K70: 14 | L70: 0.12 | M70: 61587.68 | N70: Debit Card | O70: Delivered | P70: 513230.67 | Q70: 513230.67 | R70: 69986 | S70: 8398.32
A71: ORD01707 | B71: 45297 | C71: SP01 | D71: Arjun Sharma | E71: North | F71: Agra | G71: PRD008 | H71: American Tourister Trolley | I71: Bags | J71: 4999 | K71: 18 | L71: 0.08 | M71: 82783.44 | N71: UPI | O71: Unknown | P71: 1034793 | Q71: 1034793 | R71: 89982 | S71: 7198.56
... A101: ORD02572 | B101: 45498 | C101: SP08 | D101: Kavitha Reddy | E101: West | F101: Ahmedabad | G101: PRD008 | H101: American Tourister Trolley | I101: Bags | J101: 4999 | K101: 4 | L101: 0.12 | M101: 17596.48 | N101: UPI | O101: Returned | P101: 146637.33 | Q101: 146637.33 | R101: 19996 | S101: 2399.52
A102: ORD02596 | B102: 45436 | C102: SP02 | D102: Priya Nair | E102: South | F102: Hyderabad | G102: PRD008 | H102: American Tourister Trolley | I102: Bags | J102: 4999 | K102: 8 | L102: 0 | M102: 39992 | N102: Net Banking | O102: Delivered | P102: #DIV/0! | Q102: 0 | R102: 39992 | S102: 0
A103: ORD02613 | B103: 45556 | C103: SP08 | D103: Kavitha Reddy | E103: West | F103: Pune | G103: PRD008 | H103: American Tourister Trolley | I103: Bags | J103: 4999 | K103: 20 | L103: 0.13 | M103: 86982.6 | N103: Debit Card | O103: Returned | P103: 669096.92 | Q103: 669096.92 | R103: 99980 | S103: 12997.4
A104: ORD02631 | B104: 45460 | C104: SP09 | D104: Manish Gupta | E104: North | F104: Delhi | G104: PRD008 | H104: American Tourister Trolley | I104: Bags | J104: 4999 | K104: 7 | L104: 0.11 | M104: 31143.77 | N104: Cash | O104: Delivered | P104: 283125.18 | Q104: 283125.18 | R104: 34993 | S104: 3849.23
A105: ORD02633 | B105: 45390 | C105: SP09 | D105: Manish Gupta | E105: North | F105: Chandigarh | G105: PRD008 | H105: American Tourister Trolley | I105: Bags | J105: 4999 | K105: 8 | L105: 0.08 | M105: 36792.64 | N105: EMI | O105: Delivered | P105: 459908 | Q105: 459908 | R105: 39992 | S105: 3199.36
A106: ORD02660 | B106: 45421 | C106: SP08 | D106: Kavitha Reddy | E106: West | F106: Pune | G106: PRD008 | H106: American Tourister Trolley | I106: Bags | J106: 4999 | K106: 15 | L106: 0.11 | M106: 66736.65 | N106: EMI | O106: Delivered | P106: 606696.82 | Q106: 606696.82 | R106: 74985 | S106: 8248.35
A107: ORD02689 | B107: 45330 | C107: SP03 | D107: Ravi Kumar | E107: East | F107: Guwahati | G107: PRD008 | H107: American Tourister Trolley | I107: Bags | J107: 4999 | K107: 3 | L107: 0.22 | M107: 11697.66 | N107: Net Banking | O107: Delivered | P107: 53171.182 | Q107: 53171.182 | R107: 14997 | S107: 3299.34
A108: ORD02714 | B108: 45410 | C108: SP05 | D108: Suresh Pillai | E108: South | F108: Coimbatore | G108: PRD008 | H108: American Tourister Trolley | I108: Bags | J108: 4999 | K108: 17 | L108: 0.03 | M108: 82433.51 | N108: Credit Card | O108: Pending | P108: 2747783.7 | Q108: 2747783.7 | R108: 84983 | S108: 2549.49
A109: ORD02733 | B109: 45383 | C109: SP04 | D109: Fatima Sheikh | E109: West | F109: Unknown | G109: PRD008 | H109: American Tourister Trolley | I109: Bags | J109: 4999 | K109: 15 | L109: 0.19 | M109: 60737.85 | N109: Credit Card | O109: Delivered | P109: 319672.89 | Q109: 319672.89 | R109: 74985 | S109: 14247.15
A110: ORD02781 | B110: 45319 | C110: SP02 | D110: Priya Nair | E110: South | F110: Hyderabad | G110: PRD008 | H110: American Tourister Trolley | I110: Bags | J110: 4999 | K110: 6 | L110: 0.19 | M110: 24295.14 | N110: Debit Card | O110: Delivered | P110: 127869.16 | Q110: 127869.16 | R110: 29994 | S110: 5698.86
A111: ORD02793 | B111: 45622 | C111: SP04 | D111: Fatima Sheikh | E111: West | F111: Nagpur | G111: PRD008 | H111: American Tourister Trolley | I111: Bags | J111: 4999 | K111: 7 | L111: 0.21 | M111: 27644.47 | N111: EMI | O111: Delivered | P111: 131640.33 | Q111: 131640.33 | R111: 34993 | S111: 7348.53
A112: ORD02825 | B112: 45324 | C112: SP06 | D112: Anjali Mehta | E112: North | F112: Lucknow | G112: PRD008 | H112: American Tourister Trolley | I112: Bags | J112: 4999 | K112: 17 | L112: 0 | M112: 84983 | N112: UPI | O112: Delivered | P112: #DIV/0! | Q112: 0 | R112: 84983 | S112: 0
A113: ORD02890 | B113: 45403 | C113: SP07 | D113: Rohit Verma | E113: East | F113: Guwahati | G113: PRD008 | H113: American Tourister Trolley | I113: Bags | J113: 4999 | K113: 19 | L113: 0.11 | M113: 84533.09 | N113: Cash | O113: Delivered | P113: 768482.64 | Q113: 768482.64 | R113: 94981 | S113: 10447.91
A114: ORD03008 | B114: 45365 | C114: SP03 | D114: Ravi Kumar | E114: East | F114: Patna | G114: PRD008 | H114: American Tourister Trolley | I114: Bags | J114: 4999 | K114: 17 | L114: 0.18 | M114: 69686.06 | N114: EMI | O114: Pending | P114: 387144.78 | Q114: 387144.78 | R114: 84983 | S114: 15296.94
A115: ORD03043 | B115: 45654 | C115: SP09 | D115: Manish Gupta | E115: North | F115: Chandigarh | G115: PRD008 | H115: American Tourister Trolley | I115: Bags | J115: 4999 | K115: 3 | L115: 0.1 | M115: 13497.3 | N115: Net Banking | O115: Delivered | P115: 134973 | Q115: 134973 | R115: 14997 | S115: 1499.7
A116: ORD03059 | B116: 45331 | C116: SP01 | D116: Arjun Sharma | E116: North | F116: Agra | G116: PRD008 | H116: American Tourister Trolley | I116: Bags | J116: 4999 | K116: 16 | L116: 0.12 | M116: 70385.92 | N116: UPI | O116: Delivered | P116: 586549.33 | Q116: 586549.33 | R116: 79984 | S116: 9598.08
A117: ORD03067 | B117: 45570 | C117: SP08 | D117: Kavitha Reddy | E117: West | F117: Unknown | G117: PRD008 | H117: American Tourister Trolley | I117: Bags | J117: 4999 | K117: 14 | L117: 0.29 | M117: 49690.06 | N117: Cash | O117: Delivered | P117: 171345.03 | Q117: 171345.03 | R117: 69986 | S117: 20295.94
A118: ORD03076 | B118: 45361 | C118: SP03 | D118: Ravi Kumar | E118: East | F118: Bhubaneswar | G118: PRD008 | H118: American Tourister Trolley | I118: Bags | J118: 4999 | K118: 2 | L118: 0.22 | M118: 7798.44 | N118: UPI | O118: Cancelled | P118: 35447.455 | Q118: 35447.455 | R118: 9998 | S118: 2199.56
A119: ORD03117 | B119: 45521 | C119: SP07 | D119: Rohit Verma | E119: East | F119: Kolkata | G119: PRD008 | H119: American Tourister Trolley | I119: Bags | J119: 4999 | K119: 5 | L119: 0.24 | M119: 18996.2 | N119: Net Banking | O119: Delivered | P119: 79150.833 | Q119: 79150.833 | R119: 24995 | S119: 5998.8
A120: ORD03145 | B120: 45431 | C120: SP010 | D120: Divya Iyer | E120: South | F120: Chennai | G120: PRD008 | H120: American Tourister Trolley | I120: Bags | J120: 4999 | K120: 5 | L120: 0.1 | M120: 22495.5 | N120: Net Banking | O120: Delivered | P120: 224955 | Q120: 224955 | R120: 24995 | S120: 2499.5
A121: ORD03205 | B121: 45330 | C121: SP010 | D121: Divya Iyer | E121: South | F121: Coimbatore | G121: PRD008 | H121: American Tourister Trolley | I121: Bags | J121: 4999 | K121: 8 | L121: 0.1 | M121: 35992.8 | N121: Credit Card | O121: Returned | P121: 359928 | Q121: 359928 | R121: 39992 | S121: 3999.2
A122: ORD03208 | B122: 45562 | C122: SP05 | D122: Suresh Pillai | E122: South | F122: Coimbatore | G122: PRD008 | H122: American Tourister Trolley | I122: Bags | J122: 4999 | K122: 1 | L122: 0.06 | M122: 4699.06 | N122: EMI | O122: Delivered | P122: 78317.667 | Q122: 78317.667 | R122: 4999 | S122: 299.94
A123: ORD03305 | B123: 45541 | C123: SP012 | D123: Sneha Patil | E123: West | F123: Nagpur | G123: PRD008 | H123: American Tourister Trolley | I123: Bags | J123: 4999 | K123: 19 | L123: 0.29 | M123: 67436.51 | N123: Cash | O123: Delivered | P123: 232539.69 | Q123: 232539.69 | R123: 94981 | S123: 27544.49
A124: ORD03335 | B124: 45484 | C124: SP01 | D124: Arjun Sharma | E124: North | F124: Agra | G124: PRD008 | H124: American Tourister Trolley | I124: Bags | J124: 4999 | K124: 20 | L124: 0.16 | M124: 83983.2 | N124: UPI | O124: Cancelled | P124: 524895 | Q124: 524895 | R124: 99980 | S124: 15996.8
... A294: ORD01644 | B294: 45599 | C294: SP010 | D294: Divya Iyer | E294: South | F294: Unknown | G294: PRD010 | H294: Bata Ladies Sandals | I294: Footwear | J294: 1299 | K294: 11 | L294: 0.12 | M294: 12574.32 | N294: Net Banking | O294: Delivered | P294: 104786 | Q294: 104786 | R294: 14289 | S294: 1714.68
A295: ORD01656 | B295: 45301 | C295: SP01 | D295: Arjun Sharma | E295: North | F295: Chandigarh | G295: PRD010 | H295: Bata Ladies Sandals | I295: Footwear | J295: 1299 | K295: 20 | L295: 0 | M295: 25980 | N295: Credit Card | O295: Pending | P295: #DIV/0! | Q295: 0 | R295: 25980 | S295: 0
A296: ORD01670 | B296: 45570 | C296: SP01 | D296: Arjun Sharma | E296: North | F296: Agra | G296: PRD010 | H296: Bata Ladies Sandals | I296: Footwear | J296: 1299 | K296: 6 | L296: 0.3 | M296: 5455.8 | N296: Debit Card | O296: Cancelled | P296: 18186 | Q296: 18186 | R296: 7794 | S296: 2338.2
A297: ORD01685 | B297: 45615 | C297: SP03 | D297: Ravi Kumar | E297: East | F297: Guwahati | G297: PRD010 | H297: Bata Ladies Sandals | I297: Footwear | J297: 1299 | K297: 17 | L297: 0.27 | M297: 16120.59 | N297: UPI | O297: Pending | P297: 59705.889 | Q297: 59705.889 | R297: 22083 | S297: 5962.41
A298: ORD01704 | B298: 45590 | C298: SP08 | D298: Kavitha Reddy | E298: West | F298: Pune | G298: PRD010 | H298: Bata Ladies Sandals | I298: Footwear | J298: 1299 | K298: 6 | L298: 0.04 | M298: 7482.24 | N298: Cash | O298: Pending | P298: 187056 | Q298: 187056 | R298: 7794 | S298: 311.76
A299: ORD01716 | B299: 45654 | C299: SP012 | D299: Sneha Patil | E299: West | F299: Mumbai | G299: PRD010 | H299: Bata Ladies Sandals | I299: Footwear | J299: 1299 | K299: 7 | L299: 0 | M299: 9093 | N299: Cash | O299: Delivered | P299: #DIV/0! | Q299: 0 | R299: 9093 | S299: 0
A300: ORD01734 | B300: 45550 | C300: SP012 | D300: Sneha Patil | E300: West | F300: Mumbai | G300: PRD010 | H300: Bata Ladies Sandals | I300: Footwear | J300: 1299 | K300: 19 | L300: 0.07 | M300: 22953.33 | N300: Credit Card | O300: Delivered | P300: 327904.71 | Q300: 327904.71 | R300: 24681 | S300: 1727.67
A301: ORD01763 | B301: 45574 | C301: SP05 | D301: Suresh Pillai | E301: South | F301: Coimbatore | G301: PRD010 | H301: Bata Ladies Sandals | I301: Footwear | J301: 1299 | K301: 6 | L301: 0.01 | M301: 7716.06 | N301: EMI | O301: Returned | P301: 771606 | Q301: 771606 | R301: 7794 | S301: 77.94
A302: ORD01765 | B302: 45417 | C302: SP01 | D302: Arjun Sharma | E302: North | F302: Agra | G302: PRD010 | H302: Bata Ladies Sandals | I302: Footwear | J302: 1299 | K302: 16 | L302: 0.02 | M302: 20368.32 | N302: Credit Card | O302: Delivered | P302: 1018416 | Q302: 1018416 | R302: 20784 | S302: 415.68
A303: ORD01820 | B303: 45418 | C303: SP06 | D303: Anjali Mehta | E303: North | F303: Delhi | G303: PRD010 | H303: Bata Ladies Sandals | I303: Footwear | J303: 1299 | K303: 8 | L303: 0.19 | M303: 8417.52 | N303: EMI | O303: Delivered | P303: 44302.737 | Q303: 44302.737 | R303: 10392 | S303: 1974.48
A304: ORD01863 | B304: 45329 | C304: SP09 | D304: Manish Gupta | E304: North | F304: Jaipur | G304: PRD010 | H304: Bata Ladies Sandals | I304: Footwear | J304: 1299 | K304: 12 | L304: 0.23 | M304: 12002.76 | N304: UPI | O304: Delivered | P304: 52185.913 | Q304: 52185.913 | R304: 15588 | S304: 3585.24
A305: ORD01866 | B305: 45560 | C305: SP06 | D305: Anjali Mehta | E305: North | F305: Jaipur | G305: PRD010 | H305: Bata Ladies Sandals | I305: Footwear | J305: 1299 | K305: 12 | L305: 0.04 | M305: 14964.48 | N305: Net Banking | O305: Cancelled | P305: 374112 | Q305: 374112 | R305: 15588 | S305: 623.52
A306: ORD01868 | B306: 45323 | C306: SP04 | D306: Fatima Sheikh | E306: West | F306: Mumbai | G306: PRD010 | H306: Bata Ladies Sandals | I306: Footwear | J306: 1299 | K306: 5 | L306: 0.06 | M306: 6105.3 | N306: Cash | O306: Delivered | P306: 101755 | Q306: 101755 | R306: 6495 | S306: 389.7
A307: ORD01890 | B307: 45529 | C307: SP011 | D307: Nikhil Joshi | E307: East | F307: Bhubaneswar | G307: PRD010 | H307: Bata Ladies Sandals | I307: Footwear | J307: 1299 | K307: 6 | L307: 0.15 | M307: 6624.9 | N307: Unknown | O307: Delivered | P307: 44166 | Q307: 44166 | R307: 7794 | S307: 1169.1
A308: ORD01893 | B308: 45469 | C308: SP06 | D308: Anjali Mehta | E308: North | F308: Agra | G308: PRD010 | H308: Bata Ladies Sandals | I308: Footwear | J308: 1299 | K308: 11 | L308: 0.02 | M308: 14003.22 | N308: Credit Card | O308: Delivered | P308: 700161 | Q308: 700161 | R308: 14289 | S308: 285.78
A309: ORD01903 | B309: 45396 | C309: SP02 | D309: Priya Nair | E309: South | F309: Kochi | G309: PRD010 | H309: Bata Ladies Sandals | I309: Footwear | J309: 1299 | K309: 17 | L309: 0.24 | M309: 16783.08 | N309: Credit Card | O309: Delivered | P309: 69929.5 | Q309: 69929.5 | R309: 22083 | S309: 5299.92
A310: ORD01921 | B310: 45469 | C310: SP04 | D310: Fatima Sheikh | E310: West | F310: Pune | G310: PRD010 | H310: Bata Ladies Sandals | I310: Footwear | J310: 1299 | K310: 7 | L310: 0.26 | M310: 6728.82 | N310: EMI | O310: Pending | P310: 25880.077 | Q310: 25880.077 | R310: 9093 | S310: 2364.18
A311: ORD01928 | B311: 45573 | C311: SP06 | D311: Anjali Mehta | E311: North | F311: Lucknow | G311: PRD010 | H311: Bata Ladies Sandals | I311: Footwear | J311: 1299 | K311: 7 | L311: 0.03 | M311: 8820.21 | N311: Debit Card | O311: Delivered | P311: 294007 | Q311: 294007 | R311: 9093 | S311: 272.79
... A334: ORD02385 | B334: 45336 | C334: SP05 | D334: Suresh Pillai | E334: South | F334: Coimbatore | G334: PRD010 | H334: Bata Ladies Sandals | I334: Footwear | J334: 1299 | K334: 7 | L334: 0.01 | M334: 9002.07 | N334: Net Banking | O334: Returned | P334: 900207 | Q334: 900207 | R334: 9093 | S334: 90.93
A335: ORD02389 | B335: 45453 | C335: SP08 | D335: Kavitha Reddy | E335: West | F335: Mumbai | G335: PRD010 | H335: Bata Ladies Sandals | I335: Footwear | J335: 1299 | K335: 1 | L335: 0 | M335: 1299 | N335: UPI | O335: Delivered | P335: #DIV/0! | Q335: 0 | R335: 1299 | S335: 0
A336: ORD02428 | B336: 45581 | C336: SP09 | D336: Manish Gupta | E336: North | F336: Agra | G336: PRD010 | H336: Bata Ladies Sandals | I336: Footwear | J336: 1299 | K336: 13 | L336: 0.19 | M336: 13678.47 | N336: Cash | O336: Delivered | P336: 71991.947 | Q336: 71991.947 | R336: 16887 | S336: 3208.53
A337: ORD02433 | B337: 45555 | C337: SP08 | D337: Kavitha Reddy | E337: West | F337: Mumbai | G337: PRD010 | H337: Bata Ladies Sandals | I337: Footwear | J337: 1299 | K337: 8 | L337: 0.01 | M337: 10288.08 | N337: UPI | O337: Delivered | P337: 1028808 | Q337: 1028808 | R337: 10392 | S337: 103.92
A338: ORD02481 | B338: 45650 | C338: SP07 | D338: Rohit Verma | E338: East | F338: Bhubaneswar | G338: PRD010 | H338: Bata Ladies Sandals | I338: Footwear | J338: 1299 | K338: 11 | L338: 0.12 | M338: 12574.32 | N338: Cash | O338: Unknown | P338: 104786 | Q338: 104786 | R338: 14289 | S338: 1714.68
A339: ORD02483 | B339: 45432 | C339: SP02 | D339: Priya Nair | E339: South | F339: Bangalore | G339: PRD010 | H339: Bata Ladies Sandals | I339: Footwear | J339: 1299 | K339: 9 | L339: 0.15 | M339: 9937.35 | N339: Credit Card | O339: Cancelled | P339: 66249 | Q339: 66249 | R339: 11691 | S339: 1753.65
A340: ORD02518 | B340: 45579 | C340: SP07 | D340: Rohit Verma | E340: East | F340: Kolkata | G340: PRD010 | H340: Bata Ladies Sandals | I340: Footwear | J340: 1299 | K340: 11 | L340: 0.25 | M340: 10716.75 | N340: Net Banking | O340: Delivered | P340: 42867 | Q340: 42867 | R340: 14289 | S340: 3572.25
A341: ORD02585 | B341: 45306 | C341: SP011 | D341: Nikhil Joshi | E341: East | F341: Bhubaneswar | G341: PRD010 | H341: Bata Ladies Sandals | I341: Footwear | J341: 1299 | K341: 1 | L341: 0.16 | M341: 1091.16 | N341: Debit Card | O341: Delivered | P341: 6819.75 | Q341: 6819.75 | R341: 1299 | S341: 207.84
A342: ORD02586 | B342: 45639 | C342: SP06 | D342: Anjali Mehta | E342: North | F342: Lucknow | G342: PRD010 | H342: Bata Ladies Sandals | I342: Footwear | J342: 1299 | K342: 2 | L342: 0.18 | M342: 2130.36 | N342: Net Banking | O342: Returned | P342: 11835.333 | Q342: 11835.333 | R342: 2598 | S342: 467.64
A343: ORD02625 | B343: 45575 | C343: SP010 | D343: Divya Iyer | E343: South | F343: Bangalore | G343: PRD010 | H343: Bata Ladies Sandals | I343: Footwear | J343: 1299 | K343: 13 | L343: 0.08 | M343: 15536.04 | N343: UPI | O343: Delivered | P343: 194200.5 | Q343: 194200.5 | R343: 16887 | S343: 1350.96
A344: ORD02638 | B344: 45641 | C344: SP08 | D344: Kavitha Reddy | E344: West | F344: Surat | G344: PRD010 | H344: Bata Ladies Sandals | I344: Footwear | J344: 1299 | K344: 19 | L344: 0 | M344: 24681 | N344: Cash | O344: Cancelled | P344: #DIV/0! | Q344: 0 | R344: 24681 | S344: 0
A345: ORD02641 | B345: 45552 | C345: SP011 | D345: Nikhil Joshi | E345: East | F345: Bhubaneswar | G345: PRD010 | H345: Bata Ladies Sandals | I345: Footwear | J345: 1299 | K345: 9 | L345: 0.26 | M345: 8651.34 | N345: EMI | O345: Delivered | P345: 33274.385 | Q345: 33274.385 | R345: 11691 | S345: 3039.66
A346: ORD02649 | B346: 45305 | C346: SP08 | D346: Kavitha Reddy | E346: West | F346: Surat | G346: PRD010 | H346: Bata Ladies Sandals | I346: Footwear | J346: 1299 | K346: 14 | L346: 0.17 | M346: 15094.38 | N346: Debit Card | O346: Delivered | P346: 88790.471 | Q346: 88790.471 | R346: 18186 | S346: 3091.62
A347: ORD02678 | B347: 45505 | C347: SP011 | D347: Nikhil Joshi | E347: East | F347: Kolkata | G347: PRD010 | H347: Bata Ladies Sandals | I347: Footwear | J347: 1299 | K347: 8 | L347: 0.3 | M347: 7274.4 | N347: Debit Card | O347: Delivered | P347: 24248 | Q347: 24248 | R347: 10392 | S347: 3117.6
A348: ORD02706 | B348: 45316 | C348: SP011 | D348: Nikhil Joshi | E348: East | F348: Ranchi | G348: PRD010 | H348: Bata Ladies Sandals | I348: Footwear | J348: 1299 | K348: 7 | L348: 0.28 | M348: 6546.96 | N348: Cash | O348: Delivered | P348: 23382 | Q348: 23382 | R348: 9093 | S348: 2546.04
A349: ORD02729 | B349: 45385 | C349: SP09 | D349: Manish Gupta | E349: North | F349: Jaipur | G349: PRD010 | H349: Bata Ladies Sandals | I349: Footwear | J349: 1299 | K349: 18 | L349: 0.16 | M349: 19640.88 | N349: Cash | O349: Delivered | P349: 122755.5 | Q349: 122755.5 | R349: 23382 | S349: 3741.12
A350: ORD02762 | B350: 45508 | C350: SP04 | D350: Fatima Sheikh | E350: West | F350: Surat | G350: PRD010 | H350: Bata Ladies Sandals | I350: Footwear | J350: 1299 | K350: 14 | L350: 0.12 | M350: 16003.68 | N350: Cash | O350: Delivered | P350: 133364 | Q350: 133364 | R350: 18186 | S350: 2182.32
...

Sheet Pv tables
E2: values to display | R2: Row Labels | S2: Sum of Revenue
A3: Total Orders | B3: Total Revenue | C3: Average Order value | E3: total oders | F3: total revenue | G3: avg order | R3: Ambiguous | S3: 37121.63
A4: 2400 | B4: 1.7732628e+08 | C4: 73885.951 | E4: =TEXT(A4,"#,##") -> 2,400 | F4: =TEXT(B4/10000000,"0.0")&" Cr" -> 17.7 Cr | G4: =TEXT(C4/1000,"0.0")&" k" -> 73.9 k | R4: American Tourister Trolley | S4: 3543041.2
R5: Bajaj Mixer Grinder 750W | S5: 2542701
R6: Bata Ladies Sandals | S6: 1594054.9
R7: Boat Rockerz 450 Headphones | S7: 1955207.2
A8: Row Labels | B8: Sum of Revenue | R8: Cadbury Dairy Milk Silk | S8: 112659.55
A9: Jan | B9: 2769017.6 | R9: Cello Butterflow Pens Pk10 | S9: 88575.75
A10: Feb | B10: 893375.17 | R10: Classmate A4 Notebook 200pg | S10: 86672.8
A11: Mar | B11: 3042153 | R11: Colgate MaxFresh Toothpaste | S11: 99074.55
A12: Apr | B12: 2398970.8 | R12: Dettol Liquid Soap 250ml | S12: 150788.4
A13: May | B13: 4951091.3 | R13: Himalaya Face Wash 150ml | S13: 215236.4
A14: Jun | B14: 3357906.2 | R14: iPhone 15 128GB | S14: 79975800
A15: Jul | B15: 3213561.3 | R15: Levi's 511 Slim Jeans | S15: 2307976.4
A16: Aug | B16: 3514407.8 | R16: Maggi Noodles Pack of 12 | S16: 151848
A17: Sep | B17: 4203497.8 | R17: Peter England Formal Shirt | S17: 1289464.6
A18: Oct | B18: 3698849.5 | I18: Count of Order Status | J18: Column Labels | R18: Prestige Induction Cooktop | S18: 3893344
A19: Nov | B19: 2546192.2 | I19: Row Labels | J19: Cancelled | K19: Returned | L19: Grand Total | R19: Samsung 55" QLED TV | S19: 49117500
A20: Dec | B20: 6104315 | I20: Nikhil Joshi | J20: 18 | K20: 24 | L20: 42 | R20: Tata Gold Tea 500g | S20: 259756.25
A21: Grand Total | B21: 40693338 | I21: Rohit Verma | J21: 27 | K21: 20 | L21: 47 | R21: Whirlpool 7kg Washing Machine | S21: 22676500
I22: Ravi Kumar | J22: 26 | K22: 15 | L22: 41 | R22: Wildcraft 50L Backpack | S22: 2931452
A23: Row Labels | B23: Sum of Revenue | I23: Grand Total | J23: 71 | K23: 59 | L23: 130 | R23: Woodland Men Boots | S23: 4297506.8
A24: Ravi Kumar | B24: 16462377 | R24: Grand Total | S24: 1.7732628e+08
A25: Grand Total | B25: 16462377
A27: north region at top | E27: electronics created most revenue
A28: Row Labels | B28: Sum of Revenue | E28: Row Labels | F28: Sum of Revenue
A29: North | B29: 47982458 | E29: Electronics | F29: 30069938 | I29: Count of Order Status | J29: Column Labels
A30: West | B30: 46721236 | E30: Appliances | F30: 6448011 | I30: Row Labels | J30: Cancelled | K30: Delivered | L30: Pending | M30: Returned | N30: Unknown | O30: Grand Total
A31: South | B31: 41929250 | E31: Footwear | F31: 1711747.3 | I31: Wildcraft 50L Backpack | K31: 25 | L31: 3 | M31: 6 | N31: 1 | O31: 35
A32: East | B32: 40693338 | E32: Bags | F32: 1514337 | I32: Peter England Formal Shirt | J32: 3 | K32: 17 | L32: 6 | M32: 5 | N32: 1 | O32: 32
A33: Grand Total | B33: 1.7732628e+08 | E33: Clothing | F33: 596500.63 | I33: Whirlpool 7kg Washing Machine | J33: 3 | K33: 16 | L33: 1 | M33: 5 | N33: 1 | O33: 26
E34: Grand Total | F34: 40340534 | I34: Bata Ladies Sandals | J34: 4 | K34: 23 | L34: 4 | M34: 5 | N34: 2 | O34: 38
I35: Prestige Induction Cooktop | J35: 1 | K35: 22 | M35: 5 | N35: 1 | O35: 29
A36: Row Labels | B36: Count of Order ID | I36: Classmate A4 Notebook 200pg | J36: 2 | K36: 22 | L36: 2 | M36: 5 | O36: 31
A37: Kavitha Reddy | B37: 219 | I37: Dettol Liquid Soap 250ml | J37: 2 | K37: 17 | L37: 1 | M37: 4 | N37: 1 | O37: 25
A38: Grand Total | B38: 219 | I38: Cello Butterflow Pens Pk10 | J38: 7 | K38: 24 | L38: 5 | M38: 3 | N38: 1 | O38: 40
I39: Tata Gold Tea 500g | J39: 6 | K39: 16 | L39: 3 | M39: 3 | O39: 28
A40: top 5 best selling products | I40: Samsung 55" QLED TV | J40: 2 | K40: 19 | L40: 4 | M40: 3 | N40: 2 | O40: 30
A41: Row Labels | B41: Sum of Revenue | E41: variance of UP per category | I41: Maggi Noodles Pack of 12 | J41: 4 | K41: 23 | L41: 5 | M41: 3 | N41: 1 | O41: 36
A42: iPhone 15 128GB | B42: 79975800 | E42: Row Labels | F42: Sum of Unit Price | I42: Himalaya Face Wash 150ml | J42: 3 | K42: 29 | L42: 4 | M42: 3 | N42: 2 | O42: 41
A43: Samsung 55" QLED TV | B43: 49117500 | E43: Electronics | F43: 3482145 | I43: Boat Rockerz 450 Headphones | J43: 6 | K43: 18 | L43: 3 | M43: 2 | O43: 29
A44: Whirlpool 7kg Washing Machine | B44: 22676500 | E44: Appliances | F44: 742500 | I44: iPhone 15 128GB | J44: 5 | K44: 17 | L44: 2 | M44: 2 | O44: 26
A45: Woodland Men Boots | B45: 4297506.8 | E45: Bags | F45: 177447 | I45: Colgate MaxFresh Toothpaste | J45: 5 | K45: 20 | L45: 4 | M45: 2 | N45: 2 | O45: 33
A46: Prestige Induction Cooktop | B46: 3893344 | E46: Footwear | F46: 175326 | I46: Woodland Men Boots | J46: 2 | K46: 30 | L46: 1 | M46: 1 | N46: 2 | O46: 36
A47: Grand Total | B47: 1.5996065e+08 | E47: Clothing | F47: 80851 | I47: Bajaj Mixer Grinder 750W | J47: 7 | K47: 22 | L47: 6 | M47: 1 | N47: 1 | O47: 37
E48: Food & Bev | F48: 17261 | I48: Cadbury Dairy Milk Silk | J48: 4 | K48: 29 | L48: 3 | M48: 1 | N48: 2 | O48: 39
A49: top 5 products by qunatity | E49: Personal Care | F49: 14345 | I49: American Tourister Trolley | J49: 2 | K49: 15 | L49: 1 | O49: 18
A50: Row Labels | B50: Sum of Quantity | E50: Stationery | F50: 5635 | I50: Levi's 511 Slim Jeans | J50: 3 | K50: 12 | L50: 1 | N50: 1 | O50: 17
A51: Woodland Men Boots | B51: 1441 | E51: Grand Total | F51: 4695510 | I51: Grand Total | J51: 71 | K51: 416 | L51: 59 | M51: 59 | N51: 21 | O51: 626
A52: Prestige Induction Cooktop | B52: 1429
A53: Bata Ladies Sandals | B53: 1426
A54: Bajaj Mixer Grinder 750W | B54: 1422
A55: Cadbury Dairy Milk Silk | B55: 1400
A56: Grand Total | B56: 7118 | E56: Order status breakdown
E57: Row Labels | F57: Sum of Revenue
A58: product with highest discount | E58: Cancelled | F58: 5594479.7
A59: Row Labels | B59: Average of Discount | E59: Delivered | F59: 25448308
A60: Colgate MaxFresh Toothpaste | B60: 0.17 | E60: Pending | F60: 3818285.1
A61: Grand Total | B61: 0.17 | E61: Returned | F61: 4503732.6
E62: Unknown | F62: 1328532.6
E63: Grand Total | F63: 40693338
A67: Row Labels | B67: Sum of Revenue
A68: Nikhil Joshi | B68: 8087367
A69: Ravi Kumar | B69: 16462377
A70: Rohit Verma | B70: 16143594
A71: Grand Total | B71: 40693338
I77: There is no relationship between discount and revenue
A84: Row Labels | B84: Average of Discount | C84: Sum of Check overdiscounting | D84: Sum of Revenue | E84: Arjun Sharma is over-discountingn
A85: Arjun Sharma | B85: 0.15482234 | C85: 1.3411961e+08 | D85: 11846124
A86: Anjali Mehta | B86: 0.15389189 | C86: 2.1417251e+08 | D86: 13367296
A87: Ravi Kumar | B87: 0.15102804 | C87: 2.5755115e+08 | D87: 16462377
A88: Nikhil Joshi | B88: 0.14901961 | C88: 1.5060957e+08 | D88: 8087367
A89: Fatima Sheikh | B89: 0.14873016 | C89: 2.3714588e+08 | D89: 14186030
A90: Priya Nair | B90: 0.14757426 | C90: 2.7778771e+08 | D90: 10067853
A91: Rohit Verma | B91: 0.14649038 | C91: 2.0698587e+08 | D91: 16143594
A92: Sneha Patil | B92: 0.14593909 | C92: 2.3870597e+08 | D92: 16240958
A93: Divya Iyer | B93: 0.14208122 | C93: 3.0763657e+08 | D93: 16654510
A94: Manish Gupta | B94: 0.1406383 | C94: 4.3072113e+08 | D94: 22769039
A95: Suresh Pillai | B95: 0.1394 | C95: 2.6270247e+08 | D95: 15206887
A96: Kavitha Reddy | B96: 0.13630137 | C96: 2.9671124e+08 | D96: 16294247
A97: Grand Total | B97: 0.14624583 | C97: 3.0148497e+09 | D97: 1.7732628e+08
A99: Row Labels | B99: Sum of Revenue | C99: Average of Discount | D99: Sum of Check overdiscounting | E99: Ambiguous products are over-discounting
A100: Appliances | B100: 29112545 | C100: 0.14237467 | D100: 5.598863e+08 | G100: Sum of Original revenue | H100: Sum of Revenue | I100: Sum of revenue lost due to discount
A101: Bags | B101: 6474493.2 | C101: 0.14465438 | D101: 85384421 | G101: 206834247 | H101: 1.7732628e+08 | I101: 29507965
A102: Food & Bev | B102: 524263.8 | C102: 0.1454142 | D102: 7750206.5
A103: Footwear | B103: 5891561.6 | C103: 0.14579926 | D103: 1.0562098e+08
A104: Electronics | B104: 1.3104851e+08 | C104: 0.14672269 | D104: 2.2000202e+09
A105: Stationery | B105: 175248.55 | C105: 0.14676349 | D105: 2730410.4
A106: Clothing | B106: 3597441 | C106: 0.14793991 | D106: 46921055
A107: Personal Care | B107: 465099.35 | C107: 0.15 | D107: 6362097.1
A108: Ambiguous | B108: 37121.63 | C108: 0.18 | D108: 173982.27
A109: Grand Total | B109: 1.7732628e+08 | C109: 0.14624583 | D109: 3.0148497e+09
A111: Sum of revenue lost due to discount | D111: value display
A112: 29507965 | D112: =TEXT(A112/10000000,"0.0")&" Cr" -> 3.0 Cr
A115: Row Labels | B115: Sum of Revenue
A116: Unknown | B116: 1792110
A117: UPI | B117: 22635967
A118: Debit Card | B118: 28849494
A119: Net Banking | B119: 29302383
A120: EMI | B120: 30254973
...

Sheet Dashboard

Sheet Sheet3
